japana/__init__.py
japana/dictionary.py
japana/kanji_count.py
japana/progress_bar.py
japana/word_classifier.py
japana/word_count.py
japana-1.3.dist-info/LICENSE
japana-1.3.dist-info/METADATA
japana-1.3.dist-info/WHEEL
japana-1.3.dist-info/top_level.txt
japana-1.3.dist-info/RECORD
