Metadata-Version: 2.1
Name: japana
Version: 1.3
Summary: Japanese text analysis
Home-page: https://github.com/reem-codes/japana
Author: reem-codes | Reem Ali Alghamdi
Author-email: reem.brain@gmail.com
License: MIT
Platform: UNKNOWN
Classifier: Programming Language :: Python :: 3
Classifier: License :: OSI Approved :: MIT License
Classifier: Operating System :: OS Independent
Requires-Dist: chirptext (==0.1a18)
Requires-Dist: Janome (==0.3.9)
Requires-Dist: jamdict (==0.1a5)
Requires-Dist: lxml (==4.3.4)
Requires-Dist: mecab-python3 (==0.996.2)
Requires-Dist: puchikarui (==0.1a2)
Requires-Dist: style (==1.1.0)
Requires-Dist: update (==0.0.1)
